{"events":[{"params":[1],"time":7058.82352941176,"name":"Camera Movement"},{"params":[0],"time":12705.8823529412,"name":"Camera Movement"},{"params":[187],"time":12705.8823529412,"name":"BPM Change"},{"params":[1],"time":17839.5721925134,"name":"Camera Movement"},{"params":[0],"time":22973.2620320856,"name":"Camera Movement"},{"params":[1],"time":25540.1069518717,"name":"Camera Movement"},{"params":[0],"time":28106.9518716578,"name":"Camera Movement"},{"params":[1],"time":30673.7967914439,"name":"Camera Movement"},{"params":[0],"time":33240.64171123,"name":"Camera Movement"},{"params":[1],"time":35807.486631016,"name":"Camera Movement"},{"params":[0],"time":38374.3315508021,"name":"Camera Movement"},{"params":[1],"time":40941.1764705882,"name":"Camera Movement"},{"params":[0],"time":43508.0213903743,"name":"Camera Movement"},{"params":[1],"time":46074.8663101604,"name":"Camera Movement"},{"params":[0],"time":48641.7112299465,"name":"Camera Movement"},{"params":[1],"time":51208.5561497326,"name":"Camera Movement"},{"params":[0],"time":53775.4010695187,"name":"Camera Movement"},{"params":[1],"time":61475.9358288769,"name":"Camera Movement"},{"params":[0],"time":74310.1604278074,"name":"Camera Movement"},{"params":[1],"time":82010.6951871657,"name":"Camera Movement"}],"codenameChart":true,"strumLines":[{"keyCount":4,"position":"dad","notes":[{"id":2,"sLen":0,"time":1058.82352941176,"type":0},{"id":3,"sLen":0,"time":1147.05882352941,"type":0},{"id":1,"sLen":0,"time":1235.29411764706,"type":0},{"id":0,"sLen":0,"time":1323.52941176471,"type":0},{"id":2,"sLen":0,"time":1411.76470588235,"type":0},{"id":1,"sLen":0,"time":1455.88235294118,"type":0},{"id":0,"sLen":0,"time":1500,"type":0},{"id":3,"sLen":0,"time":1588.23529411765,"type":0},{"id":0,"sLen":0,"time":1764.70588235294,"type":0},{"id":3,"sLen":0,"time":1941.17647058824,"type":0},{"id":0,"sLen":0,"time":2117.64705882353,"type":0},{"id":1,"sLen":0,"time":2161.76470588235,"type":0},{"id":2,"sLen":0,"time":2205.88235294118,"type":0},{"id":0,"sLen":0,"time":2294.11764705882,"type":0},{"id":3,"sLen":0,"time":2382.35294117647,"type":0},{"id":2,"sLen":0,"time":2470.58823529412,"type":0},{"id":0,"sLen":0,"time":2558.82352941176,"type":0},{"id":1,"sLen":0,"time":2647.05882352941,"type":0},{"id":2,"sLen":0,"time":2823.52941176471,"type":0},{"id":1,"sLen":0,"time":2867.64705882353,"type":0},{"id":0,"sLen":0,"time":2911.76470588235,"type":0},{"id":3,"sLen":0,"time":3000,"type":0},{"id":0,"sLen":0,"time":3176.47058823529,"type":0},{"id":3,"sLen":0,"time":3352.94117647059,"type":0},{"id":2,"sLen":0,"time":3441.17647058824,"type":0},{"id":1,"sLen":0,"time":3529.41176470588,"type":0},{"id":3,"sLen":0,"time":3794.11764705882,"type":0},{"id":0,"sLen":0,"time":4058.82352941176,"type":0},{"id":2,"sLen":0,"time":4235.29411764706,"type":0},{"id":1,"sLen":0,"time":4279.41176470588,"type":0},{"id":0,"sLen":0,"time":4323.52941176471,"type":0},{"id":3,"sLen":0,"time":4411.76470588235,"type":0},{"id":0,"sLen":0,"time":4588.23529411765,"type":0},{"id":3,"sLen":0,"time":4764.70588235294,"type":0},{"id":0,"sLen":0,"time":4941.17647058824,"type":0},{"id":1,"sLen":0,"time":4985.29411764706,"type":0},{"id":2,"sLen":0,"time":5029.41176470588,"type":0},{"id":0,"sLen":0,"time":5117.64705882353,"type":0},{"id":3,"sLen":0,"time":5205.88235294118,"type":0},{"id":2,"sLen":0,"time":5294.11764705882,"type":0},{"id":0,"sLen":0,"time":5382.35294117647,"type":0},{"id":1,"sLen":0,"time":5470.58823529412,"type":0},{"id":0,"sLen":0,"time":5647.05882352941,"type":0},{"id":2,"sLen":0,"time":5691.17647058824,"type":0},{"id":3,"sLen":0,"time":5735.29411764706,"type":0},{"id":1,"sLen":0,"time":5823.52941176471,"type":0},{"id":2,"sLen":0,"time":6000,"type":0},{"id":1,"sLen":0,"time":6176.47058823529,"type":0},{"id":3,"sLen":0,"time":6352.94117647059,"type":0},{"id":2,"sLen":0,"time":6529.41176470588,"type":0},{"id":0,"sLen":0,"time":6617.64705882353,"type":0},{"id":1,"sLen":0,"time":6705.88235294118,"type":0},{"id":3,"sLen":0,"time":6794.11764705882,"type":0},{"id":2,"sLen":0,"time":6882.35294117647,"type":0},{"id":1,"sLen":0,"time":6970.58823529412,"type":0},{"id":0,"sLen":266.999999999998,"time":7058.82352941176,"type":0},{"id":3,"sLen":0,"time":7411.76470588235,"type":0},{"id":3,"sLen":0,"time":7588.23529411765,"type":0},{"id":1,"sLen":0,"time":7764.70588235294,"type":0},{"id":1,"sLen":0,"time":8117.64705882353,"type":0},{"id":0,"sLen":0,"time":8294.11764705882,"type":0},{"id":1,"sLen":0,"time":8382.35294117647,"type":0},{"id":2,"sLen":0,"time":8470.58823529412,"type":0},{"id":3,"sLen":0,"time":8558.82352941176,"type":0},{"id":0,"sLen":0,"time":8647.05882352941,"type":0},{"id":3,"sLen":0,"time":8735.29411764706,"type":0},{"id":0,"sLen":0,"time":8823.52941176471,"type":0},{"id":0,"sLen":0,"time":9000,"type":0},{"id":1,"sLen":0,"time":9176.47058823529,"type":0},{"id":2,"sLen":0,"time":9352.94117647059,"type":0},{"id":3,"sLen":0,"time":9441.17647058823,"type":0},{"id":1,"sLen":0,"time":9529.41176470588,"type":0},{"id":2,"sLen":0,"time":9705.88235294118,"type":0},{"id":0,"sLen":0,"time":9794.11764705882,"type":0},{"id":3,"sLen":0,"time":9882.35294117647,"type":0},{"id":2,"sLen":0,"time":9970.58823529412,"type":0},{"id":1,"sLen":0,"time":10058.8235294118,"type":0},{"id":0,"sLen":0,"time":10147.0588235294,"type":0},{"id":2,"sLen":0,"time":10235.2941176471,"type":0},{"id":2,"sLen":0,"time":10411.7647058824,"type":0},{"id":1,"sLen":0,"time":10588.2352941176,"type":0},{"id":2,"sLen":0,"time":10764.7058823529,"type":0},{"id":3,"sLen":0,"time":10852.9411764706,"type":0},{"id":1,"sLen":0,"time":10941.1764705882,"type":0},{"id":2,"sLen":0,"time":11117.6470588235,"type":0},{"id":0,"sLen":0,"time":11205.8823529412,"type":0},{"id":3,"sLen":0,"time":11294.1176470588,"type":0},{"id":2,"sLen":0,"time":11382.3529411765,"type":0},{"id":1,"sLen":0,"time":11470.5882352941,"type":0},{"id":0,"sLen":0,"time":11558.8235294118,"type":0},{"id":2,"sLen":0,"time":11647.0588235294,"type":0},{"id":3,"sLen":0,"time":11823.5294117647,"type":0},{"id":1,"sLen":0,"time":12000,"type":0},{"id":3,"sLen":0,"time":12705.8823529412,"type":0},{"id":2,"sLen":0,"time":12745.9893048128,"type":0},{"id":0,"sLen":0,"time":12786.0962566845,"type":0},{"id":1,"sLen":0,"time":12866.3101604278,"type":0},{"id":3,"sLen":0,"time":13026.7379679144,"type":0},{"id":1,"sLen":0,"time":13187.1657754011,"type":0},{"id":2,"sLen":0,"time":13347.5935828877,"type":0},{"id":3,"sLen":0,"time":13508.0213903743,"type":0},{"id":1,"sLen":0,"time":13668.449197861,"type":0},{"id":0,"sLen":0,"time":13828.8770053476,"type":0},{"id":3,"sLen":0,"time":13989.3048128342,"type":0},{"id":2,"sLen":0,"time":14029.4117647059,"type":0},{"id":0,"sLen":0,"time":14069.5187165775,"type":0},{"id":1,"sLen":0,"time":14149.7326203209,"type":0},{"id":3,"sLen":0,"time":14310.1604278075,"type":0},{"id":1,"sLen":0,"time":14470.5882352941,"type":0},{"id":2,"sLen":0,"time":14631.0160427807,"type":0},{"id":0,"sLen":0,"time":14791.4438502674,"type":0},{"id":1,"sLen":243,"time":14951.871657754,"type":0},{"id":3,"sLen":0,"time":15272.7272727273,"type":0},{"id":2,"sLen":0,"time":15312.8342245989,"type":0},{"id":0,"sLen":0,"time":15352.9411764706,"type":0},{"id":1,"sLen":0,"time":15433.1550802139,"type":0},{"id":3,"sLen":0,"time":15593.5828877005,"type":0},{"id":1,"sLen":0,"time":15754.0106951872,"type":0},{"id":2,"sLen":0,"time":15914.4385026738,"type":0},{"id":0,"sLen":0,"time":16074.8663101604,"type":0},{"id":1,"sLen":0,"time":16235.2941176471,"type":0},{"id":0,"sLen":0,"time":16395.7219251337,"type":0},{"id":2,"sLen":0,"time":16556.1497326203,"type":0},{"id":3,"sLen":0,"time":16716.577540107,"type":0},{"id":1,"sLen":0,"time":16877.0053475936,"type":0},{"id":2,"sLen":0,"time":17037.4331550802,"type":0},{"id":0,"sLen":0,"time":17197.8609625668,"type":0},{"id":2,"sLen":0,"time":17518.7165775401,"type":0},{"id":1,"sLen":0,"time":17598.9304812834,"type":0},{"id":2,"sLen":0,"time":17679.1443850267,"type":0},{"id":3,"sLen":0,"time":17759.3582887701,"type":0},{"id":0,"sLen":0,"time":17839.5721925134,"type":0},{"id":1,"sLen":0,"time":17919.7860962567,"type":0},{"id":2,"sLen":0,"time":18000,"type":0},{"id":3,"sLen":0,"time":18080.2139037433,"type":0},{"id":1,"sLen":0,"time":18160.4278074866,"type":0},{"id":1,"sLen":0,"time":18320.8556149733,"type":0},{"id":1,"sLen":0,"time":18481.2834224599,"type":0},{"id":0,"sLen":0,"time":18802.1390374332,"type":0},{"id":1,"sLen":0,"time":18882.3529411765,"type":0},{"id":2,"sLen":0,"time":18962.5668449198,"type":0},{"id":3,"sLen":0,"time":19042.7807486631,"type":0},{"id":0,"sLen":0,"time":19122.9946524064,"type":0},{"id":1,"sLen":0,"time":19203.2085561497,"type":0},{"id":2,"sLen":0,"time":19283.422459893,"type":0},{"id":3,"sLen":0,"time":19363.6363636364,"type":0},{"id":1,"sLen":0,"time":19443.8502673797,"type":0},{"id":1,"sLen":0,"time":19604.2780748663,"type":0},{"id":3,"sLen":0,"time":19764.7058823529,"type":0},{"id":3,"sLen":0,"time":20005.3475935829,"type":0},{"id":3,"sLen":0,"time":20245.9893048128,"type":0},{"id":0,"sLen":0,"time":20406.4171122995,"type":0},{"id":1,"sLen":0,"time":20486.6310160428,"type":0},{"id":2,"sLen":0,"time":20566.8449197861,"type":0},{"id":3,"sLen":0,"time":20647.0588235294,"type":0},{"id":0,"sLen":0,"time":20727.2727272727,"type":0},{"id":1,"sLen":0,"time":20807.486631016,"type":0},{"id":2,"sLen":0,"time":20887.7005347594,"type":0},{"id":3,"sLen":0,"time":20967.9144385027,"type":0},{"id":1,"sLen":0,"time":21048.128342246,"type":0},{"id":1,"sLen":0,"time":21208.5561497326,"type":0},{"id":1,"sLen":0,"time":21368.9839572193,"type":0},{"id":0,"sLen":0,"time":21689.8395721925,"type":0},{"id":1,"sLen":0,"time":21770.0534759358,"type":0},{"id":2,"sLen":0,"time":21850.2673796791,"type":0},{"id":3,"sLen":0,"time":21930.4812834225,"type":0},{"id":0,"sLen":0,"time":22010.6951871658,"type":0},{"id":1,"sLen":0,"time":22090.9090909091,"type":0},{"id":2,"sLen":0,"time":22171.1229946524,"type":0},{"id":3,"sLen":0,"time":22251.3368983957,"type":0},{"id":0,"sLen":0,"time":22331.550802139,"type":0},{"id":1,"sLen":0,"time":22411.7647058824,"type":0},{"id":2,"sLen":0,"time":22491.9786096257,"type":0},{"id":3,"sLen":0,"time":22572.192513369,"type":0},{"id":0,"sLen":0,"time":22652.4064171123,"type":0},{"id":1,"sLen":0,"time":22732.6203208556,"type":0},{"id":3,"sLen":0,"time":22812.8342245989,"type":0},{"id":2,"sLen":0,"time":22893.0481283422,"type":0},{"id":3,"sLen":0,"time":22973.2620320856,"type":0},{"id":0,"sLen":0,"time":23053.4759358289,"type":0},{"id":3,"sLen":0,"time":23133.6898395722,"type":0},{"id":0,"sLen":0,"time":23213.9037433155,"type":0},{"id":1,"sLen":0,"time":23294.1176470588,"type":0},{"id":3,"sLen":0,"time":23454.5454545455,"type":0},{"id":0,"sLen":0,"time":23534.7593582888,"type":0},{"id":3,"sLen":0,"time":23614.9732620321,"type":0},{"id":0,"sLen":0,"time":23695.1871657754,"type":0},{"id":1,"sLen":0,"time":23775.4010695187,"type":0},{"id":3,"sLen":0,"time":23935.8288770054,"type":0},{"id":0,"sLen":0,"time":24016.0427807487,"type":0},{"id":3,"sLen":0,"time":24096.256684492,"type":0},{"id":0,"sLen":0,"time":24176.4705882353,"type":0},{"id":1,"sLen":0,"time":24256.6844919786,"type":0},{"id":3,"sLen":0,"time":24417.1122994652,"type":0},{"id":0,"sLen":0,"time":24497.3262032086,"type":0},{"id":3,"sLen":0,"time":24577.5401069519,"type":0},{"id":0,"sLen":0,"time":24657.7540106952,"type":0},{"id":2,"sLen":161.999999999996,"time":24737.9679144385,"type":0},{"id":3,"sLen":0,"time":24898.3957219251,"type":0},{"id":0,"sLen":0,"time":25058.8235294118,"type":0},{"id":2,"sLen":0,"time":25219.2513368984,"type":0},{"id":1,"sLen":0,"time":25379.679144385,"type":0},{"id":3,"sLen":242.999999999996,"time":25540.1069518717,"type":0},{"id":1,"sLen":0,"time":25860.9625668449,"type":0},{"id":0,"sLen":0,"time":26021.3903743316,"type":0},{"id":3,"sLen":0,"time":26823.5294117647,"type":0},{"id":0,"sLen":0,"time":26983.9572192513,"type":0},{"id":1,"sLen":0,"time":27144.385026738,"type":0},{"id":2,"sLen":0,"time":27304.8128342246,"type":0},{"id":3,"sLen":0,"time":28106.9518716578,"type":0},{"id":0,"sLen":0,"time":28187.1657754011,"type":0},{"id":3,"sLen":0,"time":28267.3796791444,"type":0},{"id":0,"sLen":0,"time":28347.5935828877,"type":0},{"id":1,"sLen":0,"time":28427.807486631,"type":0},{"id":3,"sLen":0,"time":28588.2352941177,"type":0},{"id":0,"sLen":0,"time":28668.449197861,"type":0},{"id":3,"sLen":0,"time":28748.6631016043,"type":0},{"id":0,"sLen":0,"time":28828.8770053476,"type":0},{"id":1,"sLen":0,"time":28909.0909090909,"type":0},{"id":3,"sLen":0,"time":29069.5187165775,"type":0},{"id":0,"sLen":0,"time":29149.7326203209,"type":0},{"id":3,"sLen":0,"time":29229.9465240642,"type":0},{"id":0,"sLen":0,"time":29310.1604278075,"type":0},{"id":2,"sLen":0,"time":29390.3743315508,"type":0},{"id":3,"sLen":0,"time":29550.8021390374,"type":0},{"id":1,"sLen":0,"time":29631.0160427808,"type":0},{"id":2,"sLen":0,"time":29711.2299465241,"type":0},{"id":3,"sLen":0,"time":29871.6577540107,"type":0},{"id":1,"sLen":0,"time":29951.871657754,"type":0},{"id":0,"sLen":161.999999999996,"time":30032.0855614973,"type":0},{"id":3,"sLen":0,"time":30192.513368984,"type":0},{"id":0,"sLen":0,"time":30352.9411764706,"type":0},{"id":2,"sLen":0,"time":30513.3689839572,"type":0},{"id":3,"sLen":243,"time":30673.7967914439,"type":0},{"id":1,"sLen":0,"time":30994.6524064171,"type":0},{"id":0,"sLen":0,"time":31155.0802139037,"type":0},{"id":3,"sLen":0,"time":31957.2192513369,"type":0},{"id":0,"sLen":0,"time":32117.6470588235,"type":0},{"id":1,"sLen":0,"time":32278.0748663102,"type":0},{"id":2,"sLen":0,"time":32438.5026737968,"type":0},{"id":3,"sLen":0,"time":32598.9304812834,"type":0},{"id":0,"sLen":0,"time":32679.1443850267,"type":0},{"id":2,"sLen":0,"time":32759.3582887701,"type":0},{"id":1,"sLen":0,"time":32839.5721925134,"type":0},{"id":3,"sLen":0,"time":32919.7860962567,"type":0},{"id":2,"sLen":0,"time":32959.8930481283,"type":0},{"id":1,"sLen":0,"time":33000,"type":0},{"id":0,"sLen":0,"time":33080.2139037433,"type":0},{"id":3,"sLen":0,"time":33160.4278074866,"type":0},{"id":2,"sLen":243,"time":33240.64171123,"type":0},{"id":0,"sLen":0,"time":33561.4973262032,"type":0},{"id":1,"sLen":0,"time":33882.3529411765,"type":0},{"id":3,"sLen":0,"time":34203.2085561497,"type":0},{"id":2,"sLen":243,"time":34524.064171123,"type":0},{"id":0,"sLen":0,"time":34844.9197860963,"type":0},{"id":1,"sLen":0,"time":35165.7754010695,"type":0},{"id":3,"sLen":0,"time":35326.2032085562,"type":0},{"id":1,"sLen":0,"time":35486.6310160428,"type":0},{"id":0,"sLen":0,"time":35647.0588235294,"type":0},{"id":2,"sLen":243,"time":35807.486631016,"type":0},{"id":3,"sLen":0,"time":36128.3422459893,"type":0},{"id":2,"sLen":243,"time":36449.1978609626,"type":0},{"id":1,"sLen":0,"time":36770.0534759358,"type":0},{"id":0,"sLen":0,"time":37090.9090909091,"type":0},{"id":0,"sLen":0,"time":37411.7647058823,"type":0},{"id":0,"sLen":0,"time":37572.192513369,"type":0},{"id":0,"sLen":0,"time":37893.0481283422,"type":0},{"id":2,"sLen":0,"time":38053.4759358289,"type":0},{"id":1,"sLen":0,"time":38213.9037433155,"type":0},{"id":3,"sLen":567,"time":38374.3315508021,"type":0},{"id":2,"sLen":243,"time":39016.0427807487,"type":0},{"id":1,"sLen":243,"time":39336.8983957219,"type":0},{"id":0,"sLen":0,"time":39657.7540106952,"type":0},{"id":1,"sLen":0,"time":39818.1818181818,"type":0},{"id":3,"sLen":0,"time":39978.6096256684,"type":0},{"id":1,"sLen":0,"time":40139.0374331551,"type":0},{"id":2,"sLen":0,"time":40299.4652406417,"type":0},{"id":0,"sLen":0,"time":40459.8930481283,"type":0},{"id":2,"sLen":0,"time":40620.320855615,"type":0},{"id":3,"sLen":0,"time":40780.7486631016,"type":0},{"id":1,"sLen":0,"time":40941.1764705882,"type":0},{"id":0,"sLen":0,"time":41101.6042780749,"type":0},{"id":1,"sLen":0,"time":41262.0320855615,"type":0},{"id":2,"sLen":0,"time":41422.4598930481,"type":0},{"id":3,"sLen":243,"time":41582.8877005347,"type":0},{"id":1,"sLen":243.000000000007,"time":41903.743315508,"type":0},{"id":0,"sLen":0,"time":42224.5989304813,"type":0},{"id":1,"sLen":0,"time":42385.0267379679,"type":0},{"id":3,"sLen":0,"time":42545.4545454545,"type":0},{"id":1,"sLen":0,"time":42705.8823529412,"type":0},{"id":0,"sLen":0,"time":42866.3101604278,"type":0},{"id":3,"sLen":0,"time":43026.7379679144,"type":0},{"id":0,"sLen":0,"time":43187.1657754011,"type":0},{"id":1,"sLen":0,"time":43347.5935828877,"type":0},{"id":2,"sLen":243.000000000007,"time":43508.0213903743,"type":0},{"id":0,"sLen":0,"time":43828.8770053476,"type":0},{"id":1,"sLen":0,"time":44149.7326203209,"type":0},{"id":3,"sLen":0,"time":44470.5882352941,"type":0},{"id":2,"sLen":243.000000000007,"time":44791.4438502674,"type":0},{"id":0,"sLen":0,"time":45112.2994652406,"type":0},{"id":3,"sLen":0,"time":45272.7272727273,"type":0},{"id":2,"sLen":0,"time":45593.5828877005,"type":0},{"id":0,"sLen":0,"time":45754.0106951871,"type":0},{"id":1,"sLen":0,"time":45914.4385026738,"type":0},{"id":2,"sLen":243.000000000015,"time":46074.8663101604,"type":0},{"id":3,"sLen":0,"time":46395.7219251337,"type":0},{"id":2,"sLen":243.000000000015,"time":46716.577540107,"type":0},{"id":1,"sLen":0,"time":47037.4331550802,"type":0},{"id":0,"sLen":0,"time":47358.2887700535,"type":0},{"id":3,"sLen":0,"time":47518.7165775401,"type":0},{"id":1,"sLen":0,"time":47679.1443850267,"type":0},{"id":0,"sLen":0,"time":47839.5721925134,"type":0},{"id":2,"sLen":0,"time":48000,"type":0},{"id":3,"sLen":0,"time":48160.4278074866,"type":0},{"id":2,"sLen":0,"time":48320.8556149733,"type":0},{"id":1,"sLen":0,"time":48481.2834224599,"type":0},{"id":3,"sLen":566.999999999985,"time":48641.7112299465,"type":0},{"id":2,"sLen":243,"time":49283.422459893,"type":0},{"id":1,"sLen":243,"time":49604.2780748663,"type":0},{"id":0,"sLen":0,"time":49925.1336898396,"type":0},{"id":1,"sLen":0,"time":50085.5614973262,"type":0},{"id":3,"sLen":0,"time":50245.9893048128,"type":0},{"id":1,"sLen":0,"time":50406.4171122995,"type":0},{"id":2,"sLen":0,"time":50566.8449197861,"type":0},{"id":0,"sLen":0,"time":50727.2727272727,"type":0},{"id":2,"sLen":0,"time":50887.7005347594,"type":0},{"id":3,"sLen":0,"time":51048.128342246,"type":0},{"id":1,"sLen":0,"time":51208.5561497326,"type":0},{"id":0,"sLen":0,"time":51368.9839572192,"type":0},{"id":1,"sLen":0,"time":51529.4117647059,"type":0},{"id":2,"sLen":0,"time":51689.8395721925,"type":0},{"id":3,"sLen":243,"time":51850.2673796791,"type":0},{"id":1,"sLen":242.999999999985,"time":52171.1229946524,"type":0},{"id":0,"sLen":0,"time":52491.9786096257,"type":0},{"id":1,"sLen":0,"time":52652.4064171123,"type":0},{"id":3,"sLen":0,"time":52812.8342245989,"type":0},{"id":1,"sLen":0,"time":52973.2620320855,"type":0},{"id":0,"sLen":0,"time":53133.6898395722,"type":0},{"id":3,"sLen":0,"time":53294.1176470588,"type":0},{"id":0,"sLen":0,"time":53454.5454545454,"type":0},{"id":1,"sLen":0,"time":53614.9732620321,"type":0},{"id":2,"sLen":567.000000000015,"time":53775.4010695187,"type":0},{"id":3,"sLen":242.999999999985,"time":55379.679144385,"type":0},{"id":1,"sLen":242.999999999985,"time":55700.5347593582,"type":0},{"id":0,"sLen":0,"time":56021.3903743315,"type":0},{"id":1,"sLen":566.999999999985,"time":56663.101604278,"type":0},{"id":2,"sLen":0,"time":57304.8128342245,"type":0},{"id":3,"sLen":0,"time":57946.5240641711,"type":0},{"id":2,"sLen":0,"time":58106.9518716577,"type":0},{"id":1,"sLen":0,"time":58267.3796791443,"type":0},{"id":0,"sLen":0,"time":58427.807486631,"type":0},{"id":2,"sLen":0,"time":58588.2352941176,"type":0},{"id":1,"sLen":0,"time":58748.6631016042,"type":0},{"id":3,"sLen":567,"time":58909.0909090909,"type":0},{"id":0,"sLen":567,"time":59550.8021390374,"type":0},{"id":1,"sLen":0,"time":60192.5133689839,"type":0},{"id":2,"sLen":0,"time":60834.2245989304,"type":0},{"id":3,"sLen":567.000000000015,"time":61475.9358288769,"type":0},{"id":0,"sLen":566.999999999985,"time":62117.6470588235,"type":0},{"id":1,"sLen":0,"time":62759.35828877,"type":0},{"id":2,"sLen":0,"time":63401.0695187165,"type":0},{"id":3,"sLen":486,"time":64042.780748663,"type":0},{"id":2,"sLen":0,"time":74310.1604278074,"type":0},{"id":3,"sLen":0,"time":74470.588235294,"type":0},{"id":1,"sLen":0,"time":74631.0160427807,"type":0},{"id":0,"sLen":0,"time":74791.4438502673,"type":0},{"id":2,"sLen":0,"time":74951.8716577539,"type":0},{"id":3,"sLen":0,"time":75112.2994652405,"type":0},{"id":1,"sLen":0,"time":75272.7272727272,"type":0},{"id":0,"sLen":0,"time":75433.1550802138,"type":0},{"id":2,"sLen":0,"time":75593.5828877004,"type":0},{"id":3,"sLen":0,"time":75754.0106951871,"type":0},{"id":1,"sLen":0,"time":75914.4385026737,"type":0},{"id":0,"sLen":0,"time":76074.8663101603,"type":0},{"id":2,"sLen":0,"time":76235.294117647,"type":0},{"id":3,"sLen":0,"time":76395.7219251336,"type":0},{"id":1,"sLen":0,"time":76556.1497326202,"type":0},{"id":0,"sLen":0,"time":76716.5775401069,"type":0},{"id":2,"sLen":0,"time":76877.0053475935,"type":0},{"id":3,"sLen":0,"time":77037.4331550801,"type":0},{"id":0,"sLen":0,"time":77117.6470588234,"type":0},{"id":1,"sLen":0,"time":77197.8609625667,"type":0},{"id":0,"sLen":0,"time":77358.2887700534,"type":0},{"id":2,"sLen":0,"time":77518.71657754,"type":0},{"id":3,"sLen":0,"time":77679.1443850266,"type":0},{"id":0,"sLen":0,"time":77759.35828877,"type":0},{"id":1,"sLen":0,"time":77839.5721925133,"type":0},{"id":0,"sLen":0,"time":77999.9999999999,"type":0},{"id":2,"sLen":0,"time":78160.4278074865,"type":0},{"id":3,"sLen":0,"time":78320.8556149732,"type":0},{"id":0,"sLen":0,"time":78401.0695187165,"type":0},{"id":1,"sLen":0,"time":78481.2834224598,"type":0},{"id":0,"sLen":0,"time":78641.7112299464,"type":0},{"id":2,"sLen":0,"time":78802.1390374331,"type":0},{"id":1,"sLen":0,"time":78882.3529411764,"type":0},{"id":3,"sLen":0,"time":78962.5668449197,"type":0},{"id":2,"sLen":0,"time":79042.780748663,"type":0},{"id":1,"sLen":0,"time":79122.9946524063,"type":0},{"id":0,"sLen":0,"time":79283.4224598929,"type":0},{"id":2,"sLen":567,"time":79443.8502673796,"type":0},{"id":3,"sLen":0,"time":80085.5614973261,"type":0},{"id":1,"sLen":0,"time":80245.9893048127,"type":0},{"id":0,"sLen":0,"time":80566.844919786,"type":0},{"id":1,"sLen":0,"time":80727.2727272726,"type":0},{"id":3,"sLen":0,"time":81048.1283422459,"type":0},{"id":1,"sLen":0,"time":81208.5561497325,"type":0},{"id":2,"sLen":567.000000000015,"time":81368.9839572191,"type":0},{"id":0,"sLen":0,"time":82010.6951871657,"type":0},{"id":0,"sLen":0,"time":83294.1176470587,"type":0},{"id":3,"sLen":0,"time":83614.973262032,"type":0},{"id":2,"sLen":0,"time":83935.8288770052,"type":0},{"id":0,"sLen":0,"time":84096.2566844919,"type":0},{"id":2,"sLen":0,"time":84176.4705882352,"type":0},{"id":1,"sLen":243,"time":84256.6844919785,"type":0},{"id":3,"sLen":567.000000000015,"time":84577.5401069518,"type":0}],"characters":["tweak"],"type":0,"visible":true},{"keyCount":4,"position":"boyfriend","notes":[{"id":2,"sLen":0,"time":7058.82352941176,"type":0},{"id":1,"sLen":0,"time":7102.94117647059,"type":0},{"id":0,"sLen":0,"time":7147.05882352941,"type":0},{"id":3,"sLen":0,"time":7235.29411764706,"type":0},{"id":0,"sLen":0,"time":7411.76470588235,"type":0},{"id":3,"sLen":0,"time":7588.23529411765,"type":0},{"id":0,"sLen":0,"time":7764.70588235294,"type":0},{"id":1,"sLen":0,"time":7808.82352941176,"type":0},{"id":2,"sLen":0,"time":7852.94117647059,"type":0},{"id":0,"sLen":0,"time":7941.17647058824,"type":0},{"id":3,"sLen":0,"time":8029.41176470588,"type":0},{"id":2,"sLen":0,"time":8117.64705882353,"type":0},{"id":0,"sLen":0,"time":8205.88235294118,"type":0},{"id":1,"sLen":0,"time":8294.11764705882,"type":0},{"id":2,"sLen":0,"time":8470.58823529412,"type":0},{"id":1,"sLen":0,"time":8514.70588235294,"type":0},{"id":0,"sLen":0,"time":8558.82352941176,"type":0},{"id":3,"sLen":0,"time":8647.05882352941,"type":0},{"id":0,"sLen":0,"time":8823.52941176471,"type":0},{"id":3,"sLen":0,"time":9000,"type":0},{"id":2,"sLen":0,"time":9088.23529411765,"type":0},{"id":1,"sLen":0,"time":9176.47058823529,"type":0},{"id":3,"sLen":0,"time":9441.17647058823,"type":0},{"id":0,"sLen":0,"time":9705.88235294118,"type":0},{"id":2,"sLen":0,"time":9882.35294117647,"type":0},{"id":1,"sLen":0,"time":9926.47058823529,"type":0},{"id":0,"sLen":0,"time":9970.58823529412,"type":0},{"id":3,"sLen":0,"time":10058.8235294118,"type":0},{"id":0,"sLen":0,"time":10235.2941176471,"type":0},{"id":3,"sLen":0,"time":10411.7647058824,"type":0},{"id":0,"sLen":0,"time":10588.2352941176,"type":0},{"id":1,"sLen":0,"time":10632.3529411765,"type":0},{"id":2,"sLen":0,"time":10676.4705882353,"type":0},{"id":0,"sLen":0,"time":10764.7058823529,"type":0},{"id":3,"sLen":0,"time":10852.9411764706,"type":0},{"id":2,"sLen":0,"time":10941.1764705882,"type":0},{"id":0,"sLen":0,"time":11029.4117647059,"type":0},{"id":1,"sLen":0,"time":11117.6470588235,"type":0},{"id":0,"sLen":0,"time":11294.1176470588,"type":0},{"id":2,"sLen":0,"time":11338.2352941176,"type":0},{"id":3,"sLen":0,"time":11382.3529411765,"type":0},{"id":1,"sLen":0,"time":11470.5882352941,"type":0},{"id":2,"sLen":0,"time":11647.0588235294,"type":0},{"id":1,"sLen":0,"time":11823.5294117647,"type":0},{"id":3,"sLen":0,"time":12000,"type":0},{"id":2,"sLen":0,"time":12176.4705882353,"type":0},{"id":0,"sLen":0,"time":12264.7058823529,"type":0},{"id":1,"sLen":0,"time":12352.9411764706,"type":0},{"id":3,"sLen":0,"time":12441.1764705882,"type":0},{"id":2,"sLen":0,"time":12529.4117647059,"type":0},{"id":1,"sLen":0,"time":12617.6470588235,"type":0},{"id":3,"sLen":0,"time":17839.5721925134,"type":0},{"id":2,"sLen":0,"time":17879.679144385,"type":0},{"id":0,"sLen":0,"time":17919.7860962567,"type":0},{"id":1,"sLen":0,"time":18000,"type":0},{"id":3,"sLen":0,"time":18160.4278074866,"type":0},{"id":1,"sLen":0,"time":18320.8556149733,"type":0},{"id":2,"sLen":0,"time":18481.2834224599,"type":0},{"id":3,"sLen":0,"time":18641.7112299465,"type":0},{"id":1,"sLen":0,"time":18802.1390374332,"type":0},{"id":0,"sLen":0,"time":18962.5668449198,"type":0},{"id":3,"sLen":0,"time":19122.9946524064,"type":0},{"id":2,"sLen":0,"time":19163.1016042781,"type":0},{"id":0,"sLen":0,"time":19203.2085561497,"type":0},{"id":1,"sLen":0,"time":19283.422459893,"type":0},{"id":3,"sLen":0,"time":19443.8502673797,"type":0},{"id":1,"sLen":0,"time":19604.2780748663,"type":0},{"id":2,"sLen":0,"time":19764.7058823529,"type":0},{"id":0,"sLen":0,"time":19925.1336898396,"type":0},{"id":1,"sLen":243,"time":20085.5614973262,"type":0},{"id":3,"sLen":0,"time":20406.4171122995,"type":0},{"id":2,"sLen":0,"time":20446.5240641711,"type":0},{"id":0,"sLen":0,"time":20486.6310160428,"type":0},{"id":1,"sLen":0,"time":20566.8449197861,"type":0},{"id":3,"sLen":0,"time":20727.2727272727,"type":0},{"id":1,"sLen":0,"time":20887.7005347594,"type":0},{"id":2,"sLen":0,"time":21048.128342246,"type":0},{"id":0,"sLen":0,"time":21208.5561497326,"type":0},{"id":1,"sLen":0,"time":21368.9839572193,"type":0},{"id":0,"sLen":0,"time":21529.4117647059,"type":0},{"id":2,"sLen":0,"time":21689.8395721925,"type":0},{"id":3,"sLen":0,"time":21850.2673796791,"type":0},{"id":1,"sLen":0,"time":22010.6951871658,"type":0},{"id":2,"sLen":0,"time":22171.1229946524,"type":0},{"id":0,"sLen":0,"time":22331.550802139,"type":0},{"id":2,"sLen":0,"time":22491.9786096257,"type":0},{"id":1,"sLen":0,"time":22572.192513369,"type":0},{"id":3,"sLen":243,"time":22652.4064171123,"type":0},{"id":3,"sLen":0,"time":25540.1069518717,"type":0},{"id":0,"sLen":0,"time":25620.320855615,"type":0},{"id":3,"sLen":0,"time":25700.5347593583,"type":0},{"id":0,"sLen":0,"time":25780.7486631016,"type":0},{"id":1,"sLen":0,"time":25860.9625668449,"type":0},{"id":3,"sLen":0,"time":26021.3903743316,"type":0},{"id":0,"sLen":0,"time":26101.6042780749,"type":0},{"id":3,"sLen":0,"time":26181.8181818182,"type":0},{"id":0,"sLen":0,"time":26262.0320855615,"type":0},{"id":1,"sLen":0,"time":26342.2459893048,"type":0},{"id":3,"sLen":0,"time":26502.6737967914,"type":0},{"id":0,"sLen":0,"time":26582.8877005348,"type":0},{"id":3,"sLen":0,"time":26663.1016042781,"type":0},{"id":0,"sLen":0,"time":26743.3155080214,"type":0},{"id":2,"sLen":0,"time":26823.5294117647,"type":0},{"id":1,"sLen":0,"time":26983.9572192513,"type":0},{"id":0,"sLen":0,"time":27064.1711229947,"type":0},{"id":2,"sLen":0,"time":27144.385026738,"type":0},{"id":0,"sLen":0,"time":27304.8128342246,"type":0},{"id":1,"sLen":0,"time":27385.0267379679,"type":0},{"id":3,"sLen":162,"time":27465.2406417112,"type":0},{"id":2,"sLen":0,"time":27625.6684491979,"type":0},{"id":0,"sLen":161.999999999985,"time":27786.0962566845,"type":0},{"id":1,"sLen":0,"time":27946.5240641711,"type":0},{"id":3,"sLen":242.999999999993,"time":28106.9518716578,"type":0},{"id":1,"sLen":0,"time":28427.807486631,"type":0},{"id":0,"sLen":0,"time":28588.2352941177,"type":0},{"id":3,"sLen":0,"time":29390.3743315508,"type":0},{"id":0,"sLen":0,"time":29550.8021390374,"type":0},{"id":1,"sLen":0,"time":29711.2299465241,"type":0},{"id":2,"sLen":0,"time":29871.6577540107,"type":0},{"id":3,"sLen":0,"time":30673.7967914439,"type":0},{"id":0,"sLen":0,"time":30754.0106951872,"type":0},{"id":3,"sLen":0,"time":30834.2245989305,"type":0},{"id":0,"sLen":0,"time":30914.4385026738,"type":0},{"id":1,"sLen":0,"time":30994.6524064171,"type":0},{"id":3,"sLen":0,"time":31155.0802139037,"type":0},{"id":0,"sLen":0,"time":31235.2941176471,"type":0},{"id":3,"sLen":0,"time":31315.5080213904,"type":0},{"id":0,"sLen":0,"time":31395.7219251337,"type":0},{"id":1,"sLen":0,"time":31475.935828877,"type":0},{"id":3,"sLen":0,"time":31636.3636363636,"type":0},{"id":0,"sLen":0,"time":31716.577540107,"type":0},{"id":3,"sLen":0,"time":31796.7914438503,"type":0},{"id":0,"sLen":0,"time":31877.0053475936,"type":0},{"id":2,"sLen":0,"time":31957.2192513369,"type":0},{"id":3,"sLen":0,"time":32117.6470588235,"type":0},{"id":1,"sLen":0,"time":32197.8609625669,"type":0},{"id":2,"sLen":0,"time":32278.0748663102,"type":0},{"id":3,"sLen":0,"time":32438.5026737968,"type":0},{"id":1,"sLen":0,"time":32518.7165775401,"type":0},{"id":0,"sLen":161.999999999993,"time":32598.9304812834,"type":0},{"id":3,"sLen":0,"time":32759.3582887701,"type":0},{"id":0,"sLen":0,"time":32919.7860962567,"type":0},{"id":2,"sLen":0,"time":33080.2139037433,"type":0},{"id":3,"sLen":1135,"time":33240.64171123,"type":0},{"id":3,"sLen":0,"time":34524.064171123,"type":0},{"id":3,"sLen":0,"time":34844.9197860963,"type":0},{"id":3,"sLen":0,"time":35005.3475935829,"type":0},{"id":3,"sLen":0,"time":35326.2032085562,"type":0},{"id":3,"sLen":0,"time":35486.6310160428,"type":0},{"id":1,"sLen":1215,"time":35807.486631016,"type":0},{"id":0,"sLen":567,"time":36449.1978609626,"type":0},{"id":2,"sLen":0,"time":37090.9090909091,"type":0},{"id":3,"sLen":0,"time":37251.3368983957,"type":0},{"id":1,"sLen":0,"time":37411.7647058823,"type":0},{"id":2,"sLen":0,"time":37572.192513369,"type":0},{"id":0,"sLen":0,"time":37732.6203208556,"type":0},{"id":1,"sLen":0,"time":37893.0481283422,"type":0},{"id":0,"sLen":0,"time":38053.4759358289,"type":0},{"id":2,"sLen":0,"time":38213.9037433155,"type":0},{"id":3,"sLen":1215,"time":38374.3315508021,"type":0},{"id":1,"sLen":0,"time":39016.0427807487,"type":0},{"id":0,"sLen":0,"time":39176.4705882353,"type":0},{"id":1,"sLen":0,"time":39336.8983957219,"type":0},{"id":2,"sLen":0,"time":39497.3262032085,"type":0},{"id":0,"sLen":567,"time":39657.7540106952,"type":0},{"id":1,"sLen":0,"time":39657.7540106952,"type":0},{"id":2,"sLen":0,"time":39818.1818181818,"type":0},{"id":3,"sLen":0,"time":39978.6096256684,"type":0},{"id":2,"sLen":0,"time":40139.0374331551,"type":0},{"id":1,"sLen":0,"time":40299.4652406417,"type":0},{"id":1,"sLen":0,"time":40620.320855615,"type":0},{"id":3,"sLen":1215,"time":40941.1764705882,"type":0},{"id":1,"sLen":0,"time":41582.8877005347,"type":0},{"id":0,"sLen":0,"time":41743.3155080214,"type":0},{"id":1,"sLen":0,"time":41903.743315508,"type":0},{"id":2,"sLen":0,"time":42064.1711229946,"type":0},{"id":0,"sLen":566.999999999985,"time":42224.5989304813,"type":0},{"id":1,"sLen":0,"time":42224.5989304813,"type":0},{"id":2,"sLen":0,"time":42385.0267379679,"type":0},{"id":3,"sLen":0,"time":42545.4545454545,"type":0},{"id":2,"sLen":0,"time":42705.8823529412,"type":0},{"id":1,"sLen":0,"time":42866.3101604278,"type":0},{"id":3,"sLen":0,"time":43026.7379679144,"type":0},{"id":1,"sLen":0,"time":43187.1657754011,"type":0},{"id":0,"sLen":0,"time":43347.5935828877,"type":0},{"id":3,"sLen":1135,"time":43508.0213903743,"type":0},{"id":3,"sLen":0,"time":44791.4438502674,"type":0},{"id":3,"sLen":0,"time":45112.2994652406,"type":0},{"id":3,"sLen":0,"time":45272.7272727273,"type":0},{"id":3,"sLen":0,"time":45593.5828877005,"type":0},{"id":3,"sLen":0,"time":45754.0106951872,"type":0},{"id":1,"sLen":1215.00000000001,"time":46074.8663101604,"type":0},{"id":0,"sLen":567.000000000015,"time":46716.577540107,"type":0},{"id":2,"sLen":0,"time":47358.2887700535,"type":0},{"id":3,"sLen":0,"time":47518.7165775401,"type":0},{"id":1,"sLen":0,"time":47679.1443850267,"type":0},{"id":2,"sLen":0,"time":47839.5721925134,"type":0},{"id":0,"sLen":0,"time":48000,"type":0},{"id":1,"sLen":0,"time":48160.4278074866,"type":0},{"id":0,"sLen":0,"time":48320.8556149733,"type":0},{"id":2,"sLen":0,"time":48481.2834224599,"type":0},{"id":3,"sLen":1214.99999999997,"time":48641.7112299465,"type":0},{"id":1,"sLen":0,"time":49283.422459893,"type":0},{"id":0,"sLen":0,"time":49443.8502673797,"type":0},{"id":1,"sLen":0,"time":49604.2780748663,"type":0},{"id":2,"sLen":0,"time":49764.7058823529,"type":0},{"id":0,"sLen":567.000000000015,"time":49925.1336898396,"type":0},{"id":1,"sLen":0,"time":49925.1336898396,"type":0},{"id":2,"sLen":0,"time":50085.5614973262,"type":0},{"id":3,"sLen":0,"time":50245.9893048128,"type":0},{"id":2,"sLen":0,"time":50406.4171122995,"type":0},{"id":1,"sLen":0,"time":50566.8449197861,"type":0},{"id":1,"sLen":0,"time":50887.7005347594,"type":0},{"id":3,"sLen":1215,"time":51208.5561497326,"type":0},{"id":1,"sLen":0,"time":51850.2673796791,"type":0},{"id":0,"sLen":0,"time":52010.6951871658,"type":0},{"id":1,"sLen":0,"time":52171.1229946524,"type":0},{"id":2,"sLen":0,"time":52331.550802139,"type":0},{"id":0,"sLen":567,"time":52491.9786096257,"type":0},{"id":1,"sLen":0,"time":52491.9786096257,"type":0},{"id":2,"sLen":0,"time":52652.4064171123,"type":0},{"id":3,"sLen":0,"time":52812.8342245989,"type":0},{"id":2,"sLen":0,"time":52973.2620320855,"type":0},{"id":1,"sLen":0,"time":53133.6898395722,"type":0},{"id":3,"sLen":0,"time":53294.1176470588,"type":0},{"id":1,"sLen":0,"time":53454.5454545454,"type":0},{"id":0,"sLen":0,"time":53614.9732620321,"type":0},{"id":2,"sLen":567.000000000015,"time":53775.4010695187,"type":0},{"id":0,"sLen":567.000000000015,"time":61475.9358288769,"type":0},{"id":2,"sLen":566.999999999985,"time":62117.6470588235,"type":0},{"id":3,"sLen":243,"time":62759.35828877,"type":0},{"id":0,"sLen":0,"time":63080.2139037432,"type":0},{"id":1,"sLen":243.000000000015,"time":63401.0695187165,"type":0},{"id":3,"sLen":242.999999999985,"time":63721.9251336898,"type":0},{"id":2,"sLen":1215.00000000001,"time":64042.780748663,"type":0},{"id":3,"sLen":243,"time":65647.0588235294,"type":0},{"id":1,"sLen":242.999999999985,"time":65967.9144385026,"type":0},{"id":0,"sLen":566.999999999985,"time":66288.7700534759,"type":0},{"id":1,"sLen":567,"time":66930.4812834224,"type":0},{"id":2,"sLen":566.999999999985,"time":67572.1925133689,"type":0},{"id":3,"sLen":0,"time":68213.9037433155,"type":0},{"id":2,"sLen":0,"time":68374.3315508021,"type":0},{"id":1,"sLen":0,"time":68534.7593582887,"type":0},{"id":0,"sLen":0,"time":68695.1871657754,"type":0},{"id":2,"sLen":0,"time":68855.614973262,"type":0},{"id":1,"sLen":0,"time":69016.0427807486,"type":0},{"id":3,"sLen":567,"time":69176.4705882352,"type":0},{"id":0,"sLen":567,"time":69818.1818181818,"type":0},{"id":1,"sLen":567,"time":70459.8930481283,"type":0},{"id":2,"sLen":567.000000000015,"time":71101.6042780748,"type":0},{"id":0,"sLen":567.000000000015,"time":71743.3155080213,"type":0},{"id":3,"sLen":567,"time":72385.0267379678,"type":0},{"id":1,"sLen":243,"time":73026.7379679143,"type":0},{"id":3,"sLen":567,"time":73668.4491978609,"type":0},{"id":2,"sLen":2511.00000000001,"time":74310.1604278074,"type":0},{"id":0,"sLen":2511,"time":76877.0053475935,"type":0},{"id":1,"sLen":2511.00000000001,"time":79443.8502673796,"type":0},{"id":1,"sLen":0,"time":82652.4064171122,"type":0},{"id":2,"sLen":0,"time":82812.8342245988,"type":0},{"id":1,"sLen":0,"time":82973.2620320854,"type":0},{"id":0,"sLen":0,"time":83133.6898395721,"type":0},{"id":3,"sLen":243.000000000029,"time":83294.1176470587,"type":0},{"id":0,"sLen":242.999999999985,"time":83614.973262032,"type":0},{"id":1,"sLen":0,"time":83935.8288770052,"type":0},{"id":3,"sLen":0,"time":84096.2566844919,"type":0},{"id":1,"sLen":0,"time":84176.4705882352,"type":0},{"id":2,"sLen":243,"time":84256.6844919785,"type":0},{"id":0,"sLen":2432,"time":84577.5401069518,"type":0}],"characters":["bfflow"],"type":1,"visible":true}],"scrollSpeed":3,"chartVersion":"1.6.0","stage":"tweak0/house","noteTypes":[]}